LICENSE.txt
evo_package_admin/__init__.py
evo_package_admin/automation/api.yaml
evo_package_admin/automation/entity.yaml
evo_package_admin/control/CAdminApi.py
evo_package_admin/control/__init__.py
evo_package_admin/entity/EAdminInput.py
evo_package_admin/entity/EAdminOutput.py
evo_package_admin/entity/EAdminQuery.py
evo_package_admin/entity/__init__.py
evo_package_admin/utility/UAdminApi.py
evo_package_admin/utility/__init__.py
evo_package_admin-2024.10.22326.dist-info/LICENSE.txt
evo_package_admin-2024.10.22326.dist-info/METADATA
evo_package_admin-2024.10.22326.dist-info/WHEEL
evo_package_admin-2024.10.22326.dist-info/RECORD
